{"ticker": "CAPR", "aliases_queried": ["CAPRICOR THERAPEUTICS INC", "CAPRICOR THERAPEUTICS INC", "Capricor Inc", "Capricor Therapeutics", "Capricor Therapeutics Inc", "capricor inc", "capricor therapeutics", "capricor therapeutics inc"], "studies": [{"protocolSection": {"identificationModule": {"nctId": "NCT04623671", "briefTitle": "Intravenous Infusion of CAP-1002 in Patients With COVID-19"}, "statusModule": {"statusVerifiedDate": "2025-01", "overallStatus": "COMPLETED", "startDateStruct": {"date": "2020-11-15"}, "primaryCompletionDateStruct": {"date": "2022-02-04"}}, "sponsorCollaboratorsModule": {"leadSponsor": {"name": "Capricor Inc."}}, "conditionsModule": {"conditions": ["Covid19"]}, "designModule": {"phases": ["PHASE2"]}}}, {"protocolSection": {"identificationModule": {"nctId": "NCT04428476", "briefTitle": "Open-label Extension of the HOPE-2 Trial"}, "statusModule": {"statusVerifiedDate": "2025-10", "overallStatus": "ACTIVE_NOT_RECRUITING", "startDateStruct": {"date": "2020-08-05"}, "primaryCompletionDateStruct": {"date": "2022-02-16"}}, "sponsorCollaboratorsModule": {"leadSponsor": {"name": "Capricor Inc."}}, "conditionsModule": {"conditions": ["Duchenne Muscular Dystrophy"]}, "designModule": {"phases": ["PHASE2"]}}}, {"protocolSection": {"identificationModule": {"nctId": "NCT02359227", "briefTitle": "Safety Study of Cenderitide in Stable Chronic Heart Failure"}, "statusModule": {"statusVerifiedDate": "2018-10", "overallStatus": "COMPLETED", "startDateStruct": {"date": "2015-01"}, "primaryCompletionDateStruct": {"date": "2015-04-02"}}, "sponsorCollaboratorsModule": {"leadSponsor": {"name": "Capricor Inc."}}, "conditionsModule": {"conditions": ["Heart Failure"]}, "designModule": {"phases": ["PHASE2"]}}}, {"protocolSection": {"identificationModule": {"nctId": "NCT02603614", "briefTitle": "Safety Study of Cenderitide in Chronic Stable Heart Failure With Moderate Renal Impairment"}, "statusModule": {"statusVerifiedDate": "2018-10", "overallStatus": "COMPLETED", "startDateStruct": {"date": "2015-12"}, "primaryCompletionDateStruct": {"date": "2016-03-31"}}, "sponsorCollaboratorsModule": {"leadSponsor": {"name": "Capricor Inc."}}, "conditionsModule": {"conditions": ["Heart Failure", "Renal Insufficiency"]}, "designModule": {"phases": ["PHASE1", "PHASE2"]}}}, {"protocolSection": {"identificationModule": {"nctId": "NCT02485938", "briefTitle": "HOPE-Duchenne (Halt cardiomyOPathy progrEssion in Duchenne)"}, "statusModule": {"statusVerifiedDate": "2025-01", "overallStatus": "COMPLETED", "startDateStruct": {"date": "2016-01-07"}, "primaryCompletionDateStruct": {"date": "2017-09-14"}}, "sponsorCollaboratorsModule": {"leadSponsor": {"name": "Capricor Inc."}}, "conditionsModule": {"conditions": ["Duchenne Muscular Dystrophy", "Cardiomyopathy"]}, "designModule": {"phases": ["PHASE2"]}}}, {"protocolSection": {"identificationModule": {"nctId": "NCT06304064", "briefTitle": "Halt cardiomyOPathy progrEssion in Duchenne (HOPE-OLE)"}, "statusModule": {"statusVerifiedDate": "2024-03", "overallStatus": "COMPLETED", "startDateStruct": {"date": "2018-06-21"}, "primaryCompletionDateStruct": {"date": "2019-03-06"}}, "sponsorCollaboratorsModule": {"leadSponsor": {"name": "Capricor Inc."}}, "conditionsModule": {"conditions": ["Duchenne Muscular Dystrophy"]}, "designModule": {"phases": ["PHASE2"]}}}, {"protocolSection": {"identificationModule": {"nctId": "NCT05126758", "briefTitle": "A Study of Deramiocel (CAP-1002) in Ambulatory and Non-Ambulatory Patients With Duchenne Muscular Dystrophy"}, "statusModule": {"statusVerifiedDate": "2025-12", "overallStatus": "ACTIVE_NOT_RECRUITING", "startDateStruct": {"date": "2022-06-22"}, "primaryCompletionDateStruct": {"date": "2025-06-18"}}, "sponsorCollaboratorsModule": {"leadSponsor": {"name": "Capricor Inc."}}, "conditionsModule": {"conditions": ["Muscular Dystrophies", "Muscular Dystrophy, Duchenne", "Muscular Disorders, Atrophic", "Muscular Diseases", "Neuromuscular Diseases", "Genetic Diseases, X-Linked", "Genetic Diseases, Inborn", "Nervous System Diseases"]}, "designModule": {"phases": ["PHASE3"]}}}, {"protocolSection": {"identificationModule": {"nctId": "NCT03406780", "briefTitle": "A Study of CAP-1002 in Ambulatory and Non-Ambulatory Patients With Duchenne Muscular Dystrophy"}, "statusModule": {"statusVerifiedDate": "2025-05", "overallStatus": "COMPLETED", "startDateStruct": {"date": "2018-04-04"}, "primaryCompletionDateStruct": {"date": "2020-03-10"}}, "sponsorCollaboratorsModule": {"leadSponsor": {"name": "Capricor Inc."}}, "conditionsModule": {"conditions": ["Muscular Dystrophies", "Muscular Dystrophy, Duchenne", "Muscular Disorders, Atrophic", "Muscular Diseases", "Neuromuscular Diseases", "Nervous System Diseases", "Genetic Diseases, X-Linked", "Genetic Diseases, Inborn"]}, "designModule": {"phases": ["PHASE2"]}}}, {"protocolSection": {"identificationModule": {"nctId": "NCT01458405", "briefTitle": "Allogeneic Heart Stem Cells to Achieve Myocardial Regeneration"}, "statusModule": {"statusVerifiedDate": "2024-02", "overallStatus": "TERMINATED", "startDateStruct": {"date": "2012-11-13"}, "primaryCompletionDateStruct": {"date": "2017-07-03"}}, "sponsorCollaboratorsModule": {"leadSponsor": {"name": "Capricor Inc."}, "collaborators": [{"name": "National Institutes of Health (NIH)"}, {"name": "National Heart, Lung, and Blood Institute (NHLBI)"}, {"name": "California Institute for Regenerative Medicine (CIRM)"}]}, "conditionsModule": {"conditions": ["Myocardial Infarction"]}, "designModule": {"phases": ["PHASE1", "PHASE2"]}}}]}